febug.py
febug-1.0.0.dist-info/METADATA
febug-1.0.0.dist-info/WHEEL
febug-1.0.0.dist-info/RECORD
