Metadata-Version: 2.1
Name: febug
Version: 1.0.0
Summary: User-space debugfs ABI wrapper library for Python
Project-URL: Homepage, https://sr.ht/~nabijaczleweli/febug
Author-email: наб <nabijaczleweli@nabijaczleweli.xyz>
License-Expression: 0BSD
Classifier: License :: OSI Approved :: Zero-Clause BSD (0BSD)
Classifier: Operating System :: MacOS
Classifier: Operating System :: POSIX :: BSD :: FreeBSD
Classifier: Operating System :: POSIX :: BSD :: NetBSD
Classifier: Operating System :: POSIX :: BSD :: OpenBSD
Classifier: Operating System :: POSIX :: Linux
Classifier: Programming Language :: Python :: 3
Requires-Python: >=3.8
